pyln/testing/__init__.py
pyln/testing/btcproxy.py
pyln/testing/db.py
pyln/testing/fixtures.py
pyln/testing/gossip.py
pyln/testing/grpc.py
pyln/testing/grpc2py.py
pyln/testing/utils.py
pyln_testing-25.12.1.dist-info/METADATA
pyln_testing-25.12.1.dist-info/WHEEL
pyln_testing-25.12.1.dist-info/RECORD
