Metadata-Version: 2.4
Name: pyln-testing
Version: 25.12.1
Summary: Test your Core Lightning integration, plugins or whatever you want
Author-email: Christian Decker <decker.christian@gmail.com>
License: BSD-MIT
Requires-Python: <4.0,>=3.9
Requires-Dist: cheroot<=10,>=8
Requires-Dist: ephemeral-port-reserve>=1.1.4
Requires-Dist: flask>=3.0.0
Requires-Dist: jsonschema>=4.4.0
Requires-Dist: psutil>=5.9.0
Requires-Dist: psycopg2-binary>=2.9.0
Requires-Dist: pyln-client>=23
Requires-Dist: pytest>=8.0.0
Requires-Dist: python-bitcoinlib>=0.11.0
Requires-Dist: requests>=2.32.0
Provides-Extra: grpc
Requires-Dist: grpcio>=1.75.0; extra == 'grpc'
Requires-Dist: pyln-grpc-proto>=0.1; extra == 'grpc'
